<pages><page bbox="0.000,0.000,720.000,540.000" id="1" rotate="0">
<normal_text archetypal_index="0" bbox="103.390,343.409,616.382,417.914" id="0" size="34.019999999999996" Annotation_index="0">NASA 
Goddard Center Director&#8217;s Colloquia <textline bbox="310.920,381.914,408.984,417.914" colourspace="Pattern" font="TimesNewRomanPS-BoldMT" ncolour="(1, 0.8, 0.4)" size="36.000">NASA </textline>
<textline bbox="103.390,343.409,616.382,375.449" colourspace="Pattern" font="TimesNewRomanPS-BoldMT" ncolour="(1, 0.8, 0.4)" size="32.040">Goddard Center Director&#8217;s Colloquia </textline>
</normal_text>
<title archetypal_index="1" bbox="72.072,212.579,647.922,310.172" id="1" size="40.019999999999996" Annotation_index="1">The Inquiring Organization 
Practical Perspectives for the 21st Century <textline bbox="73.152,262.172,646.800,310.172" colourspace="Pattern" font="TimesNewRomanPS-BoldMT" ncolour="(1, 0.8, 0.4)" size="48.000">The Inquiring Organization </textline>
<textline bbox="72.072,212.579,647.922,245.846">Practical Perspectives for the 21st Century <text bbox="72.072,212.579,91.648,244.619" colourspace="Pattern" font="TimesNewRomanPS-BoldMT" ncolour="(1, 0.8, 0.4)" size="32.040">P</text>
<text bbox="91.648,212.579,105.874,244.619" colourspace="Pattern" font="TimesNewRomanPS-BoldMT" ncolour="(1, 0.8, 0.4)" size="32.040">r</text>
<text bbox="105.874,212.579,121.894,244.619" colourspace="Pattern" font="TimesNewRomanPS-BoldMT" ncolour="(1, 0.8, 0.4)" size="32.040">a</text>
<text bbox="121.958,212.579,136.184,244.619" colourspace="Pattern" font="TimesNewRomanPS-BoldMT" ncolour="(1, 0.8, 0.4)" size="32.040">c</text>
<text bbox="136.184,212.579,146.853,244.619" colourspace="Pattern" font="TimesNewRomanPS-BoldMT" ncolour="(1, 0.8, 0.4)" size="32.040">t</text>
<text bbox="146.853,212.579,155.760,244.619" colourspace="Pattern" font="TimesNewRomanPS-BoldMT" ncolour="(1, 0.8, 0.4)" size="32.040">i</text>
<text bbox="155.760,212.579,169.986,244.619" colourspace="Pattern" font="TimesNewRomanPS-BoldMT" ncolour="(1, 0.8, 0.4)" size="32.040">c</text>
<text bbox="169.986,212.579,186.006,244.619" colourspace="Pattern" font="TimesNewRomanPS-BoldMT" ncolour="(1, 0.8, 0.4)" size="32.040">a</text>
<text bbox="186.134,212.579,195.042,244.619" colourspace="Pattern" font="TimesNewRomanPS-BoldMT" ncolour="(1, 0.8, 0.4)" size="32.040">l</text>
<text bbox="195.042,212.579,203.052,244.619" colourspace="Pattern" font="TimesNewRomanPS-BoldMT" ncolour="(1, 0.8, 0.4)" size="32.040"> </text>
<text bbox="202.699,212.579,222.276,244.619" colourspace="Pattern" font="TimesNewRomanPS-BoldMT" ncolour="(1, 0.8, 0.4)" size="32.040">P</text>
<text bbox="222.276,212.579,236.501,244.619" colourspace="Pattern" font="TimesNewRomanPS-BoldMT" ncolour="(1, 0.8, 0.4)" size="32.040">e</text>
<text bbox="236.501,212.579,250.727,244.619" colourspace="Pattern" font="TimesNewRomanPS-BoldMT" ncolour="(1, 0.8, 0.4)" size="32.040">r</text>
<text bbox="250.727,212.579,263.191,244.619" colourspace="Pattern" font="TimesNewRomanPS-BoldMT" ncolour="(1, 0.8, 0.4)" size="32.040">s</text>
<text bbox="263.255,212.579,281.069,244.619" colourspace="Pattern" font="TimesNewRomanPS-BoldMT" ncolour="(1, 0.8, 0.4)" size="32.040">p</text>
<text bbox="281.069,212.579,295.295,244.619" colourspace="Pattern" font="TimesNewRomanPS-BoldMT" ncolour="(1, 0.8, 0.4)" size="32.040">e</text>
<text bbox="295.295,212.579,309.520,244.619" colourspace="Pattern" font="TimesNewRomanPS-BoldMT" ncolour="(1, 0.8, 0.4)" size="32.040">c</text>
<text bbox="309.520,212.579,320.190,244.619" colourspace="Pattern" font="TimesNewRomanPS-BoldMT" ncolour="(1, 0.8, 0.4)" size="32.040">t</text>
<text bbox="320.190,212.579,329.097,244.619" colourspace="Pattern" font="TimesNewRomanPS-BoldMT" ncolour="(1, 0.8, 0.4)" size="32.040">i</text>
<text bbox="329.097,212.579,345.117,244.619" colourspace="Pattern" font="TimesNewRomanPS-BoldMT" ncolour="(1, 0.8, 0.4)" size="32.040">v</text>
<text bbox="345.181,212.579,359.407,244.619" colourspace="Pattern" font="TimesNewRomanPS-BoldMT" ncolour="(1, 0.8, 0.4)" size="32.040">e</text>
<text bbox="359.407,212.579,371.870,244.619" colourspace="Pattern" font="TimesNewRomanPS-BoldMT" ncolour="(1, 0.8, 0.4)" size="32.040">s</text>
<text bbox="371.870,212.579,379.880,244.619" colourspace="Pattern" font="TimesNewRomanPS-BoldMT" ncolour="(1, 0.8, 0.4)" size="32.040"> </text>
<text bbox="379.624,212.579,390.293,244.619" colourspace="Pattern" font="TimesNewRomanPS-BoldMT" ncolour="(1, 0.8, 0.4)" size="32.040">f</text>
<text bbox="390.293,212.579,406.313,244.619" colourspace="Pattern" font="TimesNewRomanPS-BoldMT" ncolour="(1, 0.8, 0.4)" size="32.040">o</text>
<text bbox="406.313,212.579,420.539,244.619" colourspace="Pattern" font="TimesNewRomanPS-BoldMT" ncolour="(1, 0.8, 0.4)" size="32.040">r</text>
<text bbox="420.058,212.579,428.068,244.619" colourspace="Pattern" font="TimesNewRomanPS-BoldMT" ncolour="(1, 0.8, 0.4)" size="32.040"> </text>
<text bbox="427.844,212.579,438.513,244.619" colourspace="Pattern" font="TimesNewRomanPS-BoldMT" ncolour="(1, 0.8, 0.4)" size="32.040">t</text>
<text bbox="438.513,212.579,456.328,244.619" colourspace="Pattern" font="TimesNewRomanPS-BoldMT" ncolour="(1, 0.8, 0.4)" size="32.040">h</text>
<text bbox="456.328,212.579,470.553,244.619" colourspace="Pattern" font="TimesNewRomanPS-BoldMT" ncolour="(1, 0.8, 0.4)" size="32.040">e</text>
<text bbox="470.553,212.579,478.563,244.619" colourspace="Pattern" font="TimesNewRomanPS-BoldMT" ncolour="(1, 0.8, 0.4)" size="32.040"> </text>
<text bbox="478.563,212.579,494.583,244.619" colourspace="Pattern" font="TimesNewRomanPS-BoldMT" ncolour="(1, 0.8, 0.4)" size="32.040">2</text>
<text bbox="494.583,212.579,510.603,244.619" colourspace="Pattern" font="TimesNewRomanPS-BoldMT" ncolour="(1, 0.8, 0.4)" size="32.040">1</text>
<text bbox="510.860,224.486,519.169,245.846" colourspace="Pattern" font="TimesNewRomanPS-BoldMT" ncolour="(1, 0.8, 0.4)" size="21.360">s</text>
<text bbox="519.140,224.486,526.253,245.846" colourspace="Pattern" font="TimesNewRomanPS-BoldMT" ncolour="(1, 0.8, 0.4)" size="21.360">t</text>
<text bbox="534.020,212.579,557.153,244.619" colourspace="Pattern" font="TimesNewRomanPS-BoldMT" ncolour="(1, 0.8, 0.4)" size="32.040">C</text>
<text bbox="557.153,212.579,571.379,244.619" colourspace="Pattern" font="TimesNewRomanPS-BoldMT" ncolour="(1, 0.8, 0.4)" size="32.040">e</text>
<text bbox="571.379,212.579,589.193,244.619" colourspace="Pattern" font="TimesNewRomanPS-BoldMT" ncolour="(1, 0.8, 0.4)" size="32.040">n</text>
<text bbox="589.193,212.579,599.862,244.619" colourspace="Pattern" font="TimesNewRomanPS-BoldMT" ncolour="(1, 0.8, 0.4)" size="32.040">t</text>
<text bbox="599.862,212.579,617.676,244.619" colourspace="Pattern" font="TimesNewRomanPS-BoldMT" ncolour="(1, 0.8, 0.4)" size="32.040">u</text>
<text bbox="617.676,212.579,631.902,244.619" colourspace="Pattern" font="TimesNewRomanPS-BoldMT" ncolour="(1, 0.8, 0.4)" size="32.040">r</text>
<text bbox="631.902,212.579,647.922,244.619" colourspace="Pattern" font="TimesNewRomanPS-BoldMT" ncolour="(1, 0.8, 0.4)" size="32.040">y</text>
</textline>
</title>
<normal_text archetypal_index="2" bbox="172.420,54.034,557.692,136.224" id="2" size="34.032" Annotation_index="2">Marilee G. Adams, Ph.D. 
November 13, 2002 <textline bbox="172.420,100.224,557.692,136.224" colourspace="Pattern" font="TimesNewRomanPS-BoldMT" ncolour="1" size="36.000">Marilee G. Adams, Ph.D. </textline>
<textline bbox="237.240,54.034,492.502,86.098" colourspace="Pattern" font="TimesNewRomanPSMT" ncolour="1" size="32.064">November 13, 2002 </textline>
</normal_text>
<curve bbox="257.640,0.125,719.870,326.640" linewidth="0" pts="448.010,0.250,719.870,0.125,719.870,48.127,257.640,326.640,277.640,311.890,294.140,299.260,312.760,283.260,330.760,266.390,357.140,237.760,380.510,207.260,397.510,180.630,412.380,153.130,424.010,125.630,432.630,100.500,438.510,79.254,443.880,52.877,446.510,29.876,448.010,0.250" Annotation_index="3" />
<curve bbox="15.998,0.000,448.080,417.720" linewidth="1" pts="15.998,417.720,266.510,380.060,448.080,204.540,448.080,0.000" Annotation_index="4" />
</page>
</pages>