<pages>
<page bbox="0.000,0.000,720.000,540.000" id="1" rotate="0">
<title archetypal_index="0" bbox="165.190,330.209,554.957,400.649" id="0" size="32.04">Weekly Summary 
Tevatron Department Meeting <textline bbox="243.820,368.609,476.110,400.649" colourspace="DeviceGray" font="TimesNewRomanPSMT" ncolour="0" size="32.040">Weekly Summary </textline>
<textline bbox="165.190,330.209,554.957,362.249" colourspace="DeviceGray" font="TimesNewRomanPSMT" ncolour="0" size="32.040">Tevatron Department Meeting </textline>
</title>
<normal_text archetypal_index="1" bbox="272.980,209.081,446.947,229.121" id="1" size="20.04">Tevatron Coordinator <textline bbox="272.980,209.081,446.947,229.121" colourspace="DeviceGray" font="TimesNewRomanPSMT" ncolour="0" size="20.040">Tevatron Coordinator </textline>
</normal_text>
<normal_text archetypal_index="2" bbox="319.800,156.281,405.331,176.321" id="2" size="20.04">Dean Still  <textline bbox="319.800,156.281,405.331,176.321" colourspace="DeviceGray" font="TimesNewRomanPSMT" ncolour="0" size="20.040">Dean Still  </textline>
</normal_text>
<normal_text archetypal_index="3" bbox="272.980,103.451,446.907,123.491" id="3" size="20.04">Friday, May 14, 2010 <textline bbox="272.980,103.451,446.907,123.491" colourspace="DeviceGray" font="TimesNewRomanPSMT" ncolour="0" size="20.040">Friday, May 14, 2010 </textline>
</normal_text>
</page>
<page bbox="0.000,0.000,720.000,540.000" id="3" mean_title="[281.54, 484.7373333333333, 481.25933333333336, 515.4413333333333]" rotate="0">
<title archetypal_index="0" bbox="293.380,482.314,486.662,514.378" id="0" size="32.064">Store Numbers <textline bbox="293.380,482.314,486.662,514.378" colourspace="DeviceGray" font="TimesNewRomanPSMT" ncolour="0" size="32.064">Store Numbers </textline>
</title>
<normal_text archetypal_index="1" bbox="61.224,9.706,230.042,23.770" id="1" size="14.064">Tevatron Coordinator - FNAL <textline bbox="61.224,9.706,230.042,23.770" colourspace="DeviceGray" font="TimesNewRomanPSMT" ncolour="0" size="14.064">Tevatron Coordinator - FNAL </textline>
</normal_text>
<normal_text archetypal_index="2" bbox="331.200,9.706,394.797,23.770" id="2" size="14.064">11/30/2020 <textline bbox="331.200,9.706,394.797,23.770" colourspace="DeviceGray" font="TimesNewRomanPSMT" ncolour="0" size="14.064">11/30/2020 </textline>
</normal_text>
<slide_number bbox="651.720,9.706,658.752,23.770" id="3" size="14.064">3 <textline bbox="651.720,9.706,658.752,23.770" colourspace="DeviceGray" font="TimesNewRomanPSMT" ncolour="0" size="14.064">3 </textline>
</slide_number>
</page>
<page bbox="0.000,0.000,720.000,540.000" id="4" mean_title="[259.26, 483.52566666666667, 512.1131666666666, 514.9096666666667]" rotate="0">
<title archetypal_index="0" bbox="236.980,482.314,542.967,514.378" id="0" size="32.064">HEP Particle Intensities <textline bbox="236.980,482.314,542.967,514.378" colourspace="DeviceGray" font="TimesNewRomanPSMT" ncolour="0" size="32.064">HEP Particle Intensities </textline>
</title>
</page>
<page bbox="0.000,0.000,720.000,540.000" id="5" mean_title="[246.796, 483.041, 527.9694999999999, 514.697]" rotate="0">
<title archetypal_index="0" bbox="228.100,482.314,551.754,514.378" id="0" size="32.064">HEP Effective Emittance <textline bbox="228.100,482.314,551.754,514.378" colourspace="DeviceGray" font="TimesNewRomanPSMT" ncolour="0" size="32.064">HEP Effective Emittance </textline>
</title>
</page>
<page bbox="0.000,0.000,720.000,540.000" id="6" mean_title="[252.724, 482.79866666666663, 523.7853333333334, 514.5906666666667]" rotate="0">
<title archetypal_index="0" bbox="264.580,482.314,515.417,514.378" id="0" size="32.064">HEP Bunch Length <textline bbox="264.580,482.314,515.417,514.378" colourspace="DeviceGray" font="TimesNewRomanPSMT" ncolour="0" size="32.064">HEP Bunch Length </textline>
</title>
</page>
<page bbox="0.000,0.000,720.000,540.000" id="7" mean_title="[272.74571428571426, 482.29104761904756, 504.8195238095238, 514.1607619047619]" rotate="0">
<title archetypal_index="0" bbox="322.800,481.022,457.405,513.086" id="0" size="32.064">Problems <textline bbox="322.800,481.022,457.405,513.086" colourspace="DeviceGray" font="BCDEEE+ComicSansMS" ncolour="0" size="32.064">Problems </textline>
</title>
<normal_text archetypal_index="1" bbox="61.224,9.706,230.042,23.770" id="4" size="14.064">Tevatron Coordinator - FNAL <textline bbox="61.224,9.706,230.042,23.770" colourspace="DeviceGray" font="TimesNewRomanPSMT" ncolour="0" size="14.064">Tevatron Coordinator - FNAL </textline>
</normal_text>
<normal_text archetypal_index="2" bbox="331.200,9.706,394.797,23.770" id="5" size="14.064">11/30/2020 <textline bbox="331.200,9.706,394.797,23.770" colourspace="DeviceGray" font="TimesNewRomanPSMT" ncolour="0" size="14.064">11/30/2020 </textline>
</normal_text>
<slide_number bbox="651.720,9.706,658.752,23.770" id="6" size="14.064">7 <textline bbox="651.720,9.706,658.752,23.770" colourspace="DeviceGray" font="TimesNewRomanPSMT" ncolour="0" size="14.064">7 </textline>
</slide_number>
<enlisting archetypal_index="3" bbox="61.224,254.696,617.994,413.971">&#8226; Still have both Pbar and Proton Longitudinal blow ups 
&#8226; Quench D34L ; No beam loss; Not fully understood. Low quench  &#8226; High Proton halo losses at start of store. 
&#8226; Store loss due to lightning. 
&#8226; Pbar vert emit growth at int collision and scalloping. <normal_text bbox="61.224,365.126,617.994,413.971" id="1" size="20.052">&#8226; Still have both Pbar and Proton Longitudinal blow ups 
&#8226; Quench D34L ; No beam loss; Not fully understood. Low quench  <textline bbox="61.224,393.931,524.274,413.971" colourspace="DeviceGray" font="TimesNewRomanPSMT" ncolour="0" size="20.040">&#8226; Still have both Pbar and Proton Longitudinal blow ups </textline>
<textline bbox="61.224,365.126,617.994,385.190" colourspace="DeviceGray" font="TimesNewRomanPSMT" ncolour="0" size="20.064">&#8226; Quench D34L ; No beam loss; Not fully understood. Low quench  </textline>
</normal_text>
<normal_text bbox="61.224,254.696,507.943,332.341" id="3" size="20.048">&#8226; High Proton halo losses at start of store. 
&#8226; Store loss due to lightning. 
&#8226; Pbar vert emit growth at int collision and scalloping. <textline bbox="61.224,312.301,407.642,332.341" colourspace="DeviceGray" font="TimesNewRomanPSMT" ncolour="0" size="20.040">&#8226; High Proton halo losses at start of store. </textline>
<textline bbox="61.224,283.501,303.113,303.541" colourspace="DeviceGray" font="TimesNewRomanPSMT" ncolour="0" size="20.040">&#8226; Store loss due to lightning. </textline>
<textline bbox="61.224,254.696,507.943,274.760" colourspace="DeviceGray" font="TimesNewRomanPSMT" ncolour="0" size="20.064">&#8226; Pbar vert emit growth at int collision and scalloping. </textline>
</normal_text>
<normal_text bbox="88.224,341.101,231.229,361.141" id="2" size="20.04">threshold magent. <textline bbox="88.224,341.101,231.229,361.141" colourspace="DeviceGray" font="TimesNewRomanPSMT" ncolour="0" size="20.040">threshold magent. </textline>
</normal_text>
</enlisting></page>
<page bbox="0.000,0.000,720.000,540.000" id="8" mean_title="[254.6242857142857, 481.9737857142857, 523.5651428571429, 513.8920714285714]" rotate="0">
<title archetypal_index="0" bbox="200.260,481.022,579.802,513.086" id="0" size="32.064">Studies/Work Completed <textline bbox="200.260,481.022,579.802,513.086" colourspace="DeviceGray" font="BCDEEE+ComicSansMS" ncolour="0" size="32.064">Studies/Work Completed </textline>
</title>
<enlisting archetypal_index="1" bbox="61.224,336.301,365.698,356.341" id="1" size="20.04">&#8226; Proton only store to smooth orbits. <textline bbox="61.224,336.301,365.698,356.341" colourspace="DeviceGray" font="TimesNewRomanPSMT" ncolour="0" size="20.040">&#8226; Proton only store to smooth orbits. </textline>
</enlisting>
<normal_text archetypal_index="2" bbox="61.224,9.706,230.042,23.770" id="2" size="14.064">Tevatron Coordinator - FNAL <textline bbox="61.224,9.706,230.042,23.770" colourspace="DeviceGray" font="TimesNewRomanPSMT" ncolour="0" size="14.064">Tevatron Coordinator - FNAL </textline>
</normal_text>
<normal_text archetypal_index="3" bbox="331.200,9.706,394.797,23.770" id="3" size="14.064">11/30/2020 <textline bbox="331.200,9.706,394.797,23.770" colourspace="DeviceGray" font="TimesNewRomanPSMT" ncolour="0" size="14.064">11/30/2020 </textline>
</normal_text>
<slide_number bbox="651.720,9.706,658.752,23.770" id="4" size="14.064">8 <textline bbox="651.720,9.706,658.752,23.770" colourspace="DeviceGray" font="TimesNewRomanPSMT" ncolour="0" size="14.064">8 </textline>
</slide_number>
</page>
<page bbox="0.000,0.000,720.000,540.000" id="9" mean_title="[259.93, 482.59183333333334, 518.6566666666666, 513.6358333333333]" rotate="0">
<title archetypal_index="0" bbox="278.500,484.755,501.477,512.739" id="0" size="27.984">Luminosity Integral <textline bbox="278.500,484.755,501.477,512.739" colourspace="DeviceGray" font="TimesNewRomanPSMT" ncolour="0" size="27.984">Luminosity Integral </textline>
</title>
<normal_text archetypal_index="1" bbox="61.224,9.706,230.042,23.770" id="1" size="14.064">Tevatron Coordinator - FNAL <textline bbox="61.224,9.706,230.042,23.770" colourspace="DeviceGray" font="TimesNewRomanPSMT" ncolour="0" size="14.064">Tevatron Coordinator - FNAL </textline>
</normal_text>
<slide_number bbox="651.720,9.706,658.752,23.770" id="3" size="14.064">9 <textline bbox="651.720,9.706,658.752,23.770" colourspace="DeviceGray" font="TimesNewRomanPSMT" ncolour="0" size="14.064">9 </textline>
</slide_number>
<picture archetypal_index="2" bbox="156.000,48.000,552.000,444.000" caption="11/30/2020 " height="396" name="Image47" src="Image47.600x600.bmp" width="396">
</picture>
</page>
<page bbox="0.000,0.000,720.000,540.000" id="10" mean_title="[267.148, 482.5362666666667, 511.74673333333334, 513.7842666666667]" rotate="0">
<title archetypal_index="0" bbox="296.020,482.314,484.107,514.378" id="0" size="32.064">Study requests <textline bbox="296.020,482.314,484.107,514.378" colourspace="DeviceGray" font="TimesNewRomanPSMT" ncolour="0" size="32.064">Study requests </textline>
</title>
<normal_text archetypal_index="1" bbox="61.224,9.706,230.042,23.770" id="6" size="14.064">Tevatron Coordinator - FNAL <textline bbox="61.224,9.706,230.042,23.770" colourspace="DeviceGray" font="TimesNewRomanPSMT" ncolour="0" size="14.064">Tevatron Coordinator - FNAL </textline>
</normal_text>
<normal_text archetypal_index="2" bbox="331.200,9.706,394.797,23.770" id="7" size="14.064">11/30/2020 <textline bbox="331.200,9.706,394.797,23.770" colourspace="DeviceGray" font="TimesNewRomanPSMT" ncolour="0" size="14.064">11/30/2020 </textline>
</normal_text>
<slide_number bbox="644.640,9.706,658.752,23.770" id="8" size="14.064">10 <textline bbox="644.640,9.706,658.752,23.770" colourspace="DeviceGray" font="TimesNewRomanPSMT" ncolour="0" size="14.064">10 </textline>
</slide_number>
<enlisting archetypal_index="3" bbox="61.224,144.281,652.711,413.971">&#8226; TEL-2 abort gap cleaning test (EOS 1 hour) 
&#8226; 150gev Chrom Study (2 hours- dedicated at 150gev, Tan) 
&#8226; Aperture scans at B0 and D0 
&#8226; Ping beam at low field to measure coupling with protons on the pbar  &#8226; Tune mults calibration. &#8226; Pbar only store once luminosity is better to document conditions. 
&#8226; Lattice measurements at Flattop and Sequence 14 and on pbar helix at  <normal_text bbox="61.224,307.501,641.248,413.971" id="1" size="20.046">&#8226; TEL-2 abort gap cleaning test (EOS 1 hour) 
&#8226; 150gev Chrom Study (2 hours- dedicated at 150gev, Tan) 
&#8226; Aperture scans at B0 and D0 
&#8226; Ping beam at low field to measure coupling with protons on the pbar  <textline bbox="61.224,393.931,439.795,413.971" colourspace="DeviceGray" font="TimesNewRomanPSMT" ncolour="0" size="20.040">&#8226; TEL-2 abort gap cleaning test (EOS 1 hour) </textline>
<textline bbox="61.224,365.126,549.452,385.190" colourspace="DeviceGray" font="TimesNewRomanPSMT" ncolour="0" size="20.064">&#8226; 150gev Chrom Study (2 hours- dedicated at 150gev, Tan) </textline>
<textline bbox="61.224,336.301,318.604,356.341" colourspace="DeviceGray" font="TimesNewRomanPSMT" ncolour="0" size="20.040">&#8226; Aperture scans at B0 and D0 </textline>
<textline bbox="61.224,307.501,641.248,327.541" colourspace="DeviceGray" font="TimesNewRomanPSMT" ncolour="0" size="20.040">&#8226; Ping beam at low field to measure coupling with protons on the pbar  </textline>
</normal_text>
<normal_text bbox="61.224,254.696,274.217,274.760" id="3" size="20.064">&#8226; Tune mults calibration. <textline bbox="61.224,254.696,274.217,274.760" colourspace="DeviceGray" font="TimesNewRomanPSMT" ncolour="0" size="20.064">&#8226; Tune mults calibration. </textline>
</normal_text>
<normal_text bbox="61.224,168.281,652.711,217.121" id="4" size="20.04">&#8226; Pbar only store once luminosity is better to document conditions. 
&#8226; Lattice measurements at Flattop and Sequence 14 and on pbar helix at  <textline bbox="61.224,197.081,608.402,217.121" colourspace="DeviceGray" font="TimesNewRomanPSMT" ncolour="(0, 0.4, 1)" size="20.040">&#8226; Pbar only store once luminosity is better to document conditions. </textline>
<textline bbox="61.224,168.281,652.711,188.321" colourspace="DeviceGray" font="TimesNewRomanPSMT" ncolour="(0, 0.4, 1)" size="20.040">&#8226; Lattice measurements at Flattop and Sequence 14 and on pbar helix at  </textline>
</normal_text>
<normal_text bbox="88.224,283.501,128.304,303.541" id="2" size="20.04">helix <textline bbox="88.224,283.501,128.304,303.541" colourspace="DeviceGray" font="TimesNewRomanPSMT" ncolour="0" size="20.040">helix </textline>
</normal_text>
<normal_text bbox="88.224,144.281,169.446,164.321" id="5" size="20.04">Collisions <textline bbox="88.224,144.281,169.446,164.321" colourspace="DeviceGray" font="TimesNewRomanPSMT" ncolour="(0, 0.4, 1)" size="20.040">Collisions </textline>
</normal_text>
</enlisting></page>
</pages>