{"1": {"Responsitivity": 1.0, "Time": 0.015364, "New slide": "frozenset({b-y(1,0), title(0), eq-x(1,0)})", "Archetype representation": "frozenset({b-y(1,0), eq-x(1,0), title(0)})", "Archetype": 1, "Master": "-1", "Best mapping": {"1": -1, "0": 0}, "Best role mapping": {"0": "Title", "1": "Content"}, "Comparisons": 120}, "2": {"Responsitivity": 1.0, "Time": 0.006119, "New slide": "frozenset({eq-x(0,1), b-y(1,0), title(0)})", "Archetype representation": "frozenset({eq-x(0,1), b-y(1,0), title(0)})", "Archetype": 5, "Master": "-1", "Best mapping": {"1": -1, "0": 0}, "Best role mapping": {"0": "Title", "1": "Subtitle"}, "Comparisons": 120}, "3": {"Responsitivity": 1.0, "Time": 0.013846, "New slide": "frozenset({eq-x(0,1), b-y(1,0), title(0)})", "Archetype representation": "frozenset({eq-x(0,1), b-y(1,0), title(0)})", "Archetype": 5, "Master": "-1", "Best mapping": {"1": -1, "0": 0}, "Best role mapping": {"0": "Title", "1": "Subtitle"}, "Comparisons": 120}, "4": {"Responsitivity": 1.0, "Time": 0.005952, "New slide": "frozenset({b-y(1,0), title(0), eq-x(1,0)})", "Archetype representation": "frozenset({b-y(1,0), eq-x(1,0), title(0)})", "Archetype": 1, "Master": "-1", "Best mapping": {"1": -1, "0": 0}, "Best role mapping": {"0": "Title", "1": "Content"}, "Comparisons": 120}, "5": {"Responsitivity": 1.0, "Time": 0.004547, "New slide": "frozenset({d-y(0,1), title(0), d-x(0,1)})", "Archetype representation": "frozenset({d-x(0,1), background(1), title(0), d-y(0,1)})", "Archetype": 8, "Master": "-1", "Best mapping": {"1": -1, "0": 0}, "Best role mapping": {"0": "Title"}, "Comparisons": 120}, "6": {"Responsitivity": 1.0, "Time": 0.005803, "New slide": "frozenset({eq-x(0,1), b-y(1,0), title(0)})", "Archetype representation": "frozenset({eq-x(0,1), b-y(1,0), title(0)})", "Archetype": 5, "Master": "-1", "Best mapping": {"1": -1, "0": 0}, "Best role mapping": {"0": "Title", "1": "Subtitle"}, "Comparisons": 120}, "7": {"Responsitivity": 1.0, "Time": 29.387942, "New slide": "frozenset({o-x(2,3), s-x(1,0), title(0), eq-y(1,2), b-x(1,3), o-x(0,3), b-x(1,2), eq-y(3,2), b-y(1,0), d-y(3,1), d-y(0,2), b-y(3,0), o-x(0,2)})", "Archetype representation": "frozenset({b-y(2,0), s-x(1,0), title(0), d-x(2,0), eq-y(1,2), eq-y(2,3), b-x(1,3), b-x(1,2), b-y(1,0), f-x(3,0), b-x(2,3), b-y(3,0), eq-y(1,3)})", "Archetype": 3, "Master": "-1", "Best mapping": {"2": -3, "3": -2, "1": -1, "0": 0}, "Best role mapping": {"0": "Title", "1": "Left Content", "2": "Middle Content", "3": "Right Content"}, "Comparisons": 120000}, "8": {"Responsitivity": 1.0, "Time": 0.006787, "New slide": "frozenset({eq-x(0,1), b-y(1,0), title(0)})", "Archetype representation": "frozenset({eq-x(0,1), b-y(1,0), title(0)})", "Archetype": 5, "Master": "-1", "Best mapping": {"1": -1, "0": 0}, "Best role mapping": {"0": "Title", "1": "Subtitle"}, "Comparisons": 120}, "9": {"Responsitivity": 1.0, "Time": 0.005801, "New slide": "frozenset({eq-x(0,1), b-y(1,0), title(0)})", "Archetype representation": "frozenset({eq-x(0,1), b-y(1,0), title(0)})", "Archetype": 5, "Master": "-1", "Best mapping": {"1": -1, "0": 0}, "Best role mapping": {"0": "Title", "1": "Subtitle"}, "Comparisons": 120}, "10": {"Responsitivity": 0.6666666666666666, "Time": 10.192028, "New slide": "frozenset({b-y(2,0), title(0), d-x(1,2), d-y(0,1), o-x(1,0), b-y(2,1), eq-x(0,2)})", "Archetype representation": "frozenset({eq-x(0,1), b-y(1,0), title(0)})", "Archetype": 5, "Master": "-1", "Best mapping": {"2": -1, "0": 0}, "Best role mapping": {"0": "Title", "1": "Subtitle"}, "Comparisons": 120060}, "11": {"Responsitivity": 1.0, "Time": 0.005774, "New slide": "frozenset({d-y(0,1), d-x(0,1), title(0), background(1)})", "Archetype representation": "frozenset({d-x(0,1), background(1), title(0), d-y(0,1)})", "Archetype": 8, "Master": "-1", "Best mapping": {"1": -1, "0": 0}, "Best role mapping": {"0": "Title"}, "Comparisons": 120}, "12": {"Responsitivity": 1.0, "Time": 0.00579, "New slide": "frozenset({eq-x(0,1), b-y(1,0), title(0)})", "Archetype representation": "frozenset({eq-x(0,1), b-y(1,0), title(0)})", "Archetype": 5, "Master": "-1", "Best mapping": {"1": -1, "0": 0}, "Best role mapping": {"0": "Title", "1": "Subtitle"}, "Comparisons": 120}}