{"1": {"Responsitivity": 1.0, "Time": 376.650301, "New slide": "frozenset({b-x(0,2), s-x(0,1), b-x(1,2), b-y(2,3), eq-y(1,3), b-x(2,3), title(0), b-y(2,0), d-y(2,1), d-y(0,1), o-y(0,3), b-x(0,3), b-x(1,3)})", "Archetype representation": "frozenset({b-y(1,0), s-x(0,1), b-x(0,2), b-x(1,2), eq-y(1,3), b-x(2,3), title(0), d-y(2,3), b-y(2,0), b-y(3,0), d-y(2,1), b-x(0,3), b-x(1,3)})", "Archetype": 3, "Master": "0", "Best mapping": {"3": -3, "2": -2, "1": -1, "0": 0}, "Best role mapping": {"0": "Title", "1": "Left Content", "2": "Middle Content", "3": "Right Content"}, "Comparisons": 161250}, "2": {"Responsitivity": 1.0, "Time": 343.869235, "New slide": "frozenset({b-y(1,0), b-y(1,2), b-x(1,2), title(0), b-x(3,2), eq-y(3,2), d-y(0,2), s-x(3,1), o-x(0,2), s-x(1,0), d-y(0,3), s-x(3,0), b-y(1,3)})", "Archetype representation": "frozenset({b-y(1,0), b-x(1,2), title(0), b-y(4,1), s-x(1,3), o-x(0,4), b-x(3,2), b-y(3,0), s-x(1,0), b-y(3,1), b-y(4,2), eq-y(1,2), b-x(1,4), b-y(3,2), b-y(2,0), s-x(3,0), s-x(2,4), b-x(3,4), o-x(0,2), d-y(3,4), b-y(4,0)})", "Archetype": 4, "Master": "0", "Best mapping": {"1": -3, "2": -2, "3": -1, "0": 0}, "Best role mapping": {"0": "Title", "1": "Left Subtitle", "2": "Right Subtitle", "3": "Left Content", "4": "Right Content"}, "Comparisons": 160500}, "3": {"Responsitivity": 1.0, "Time": 0.195131, "New slide": "frozenset({b-y(1,0), title(0), s-x(0,1)})", "Archetype representation": "frozenset({b-y(1,0), title(0), s-x(0,1)})", "Archetype": 1, "Master": "0", "Best mapping": {"1": -1, "0": 0}, "Best role mapping": {"0": "Title", "1": "Content"}, "Comparisons": 1500}, "4": {"Responsitivity": 1.0, "Time": 92.161319, "New slide": "frozenset({b-y(1,0), s-x(0,1), b-y(1,2), b-x(1,2), b-x(0,2), b-y(0,2), title(0), background(2)})", "Archetype representation": "frozenset({b-y(1,0), s-x(0,1), b-x(0,2), b-x(1,2), title(0), b-y(2,0), d-y(2,1)})", "Archetype": 2, "Master": "0", "Best mapping": {"2": -2, "1": -1, "0": 0}, "Best role mapping": {"0": "Title", "1": "Left Content", "2": "Right Content"}, "Comparisons": 160500}, "5": {"Responsitivity": 1.0, "Time": 0.011628, "New slide": "frozenset({no_title(), background(0)})", "Archetype representation": "frozenset({no_title(), background(0)})", "Archetype": 9, "Master": "0", "Best mapping": {"0": 0}, "Best role mapping": {}, "Comparisons": 0}, "6": {"Responsitivity": 1.0, "Time": 0.266152, "New slide": "frozenset({b-y(1,0), d-x(1,0), title(0)})", "Archetype representation": "frozenset({b-y(1,0), first_slide(), title(0), d-x(1,0)})", "Archetype": 0, "Master": "0", "Best mapping": {"1": -1, "0": 0}, "Best role mapping": {"0": "Title", "1": "Subtitle"}, "Comparisons": 1500}, "7": {"Responsitivity": 1.0, "Time": 0.418113, "New slide": "frozenset({b-y(1,0), title(0), s-x(0,1)})", "Archetype representation": "frozenset({b-y(1,0), title(0), s-x(0,1)})", "Archetype": 1, "Master": "0", "Best mapping": {"1": -1, "0": 0}, "Best role mapping": {"0": "Title", "1": "Content"}, "Comparisons": 1500}, "8": {"Responsitivity": 1.0, "Time": 0.418659, "New slide": "frozenset({b-y(1,0), title(0), s-x(0,1)})", "Archetype representation": "frozenset({b-y(1,0), title(0), s-x(0,1)})", "Archetype": 1, "Master": "0", "Best mapping": {"1": -1, "0": 0}, "Best role mapping": {"0": "Title", "1": "Content"}, "Comparisons": 1500}, "9": {"Responsitivity": 1.0, "Time": 137.099912, "New slide": "frozenset({d-y(2,1), b-x(1,2), d-y(0,1), o-x(0,2), s-x(1,0), title(0), d-y(0,2)})", "Archetype representation": "frozenset({b-y(1,0), b-x(1,2), title(0), b-y(2,0), d-y(2,1), o-x(0,2), s-x(1,0)})", "Archetype": 2, "Master": "0", "Best mapping": {"2": -2, "1": -1, "0": 0}, "Best role mapping": {"0": "Title", "1": "Left Content", "2": "Right Content"}, "Comparisons": 160500}, "10": {"Responsitivity": 1.0, "Time": 0.420296, "New slide": "frozenset({b-y(1,0), title(0), s-x(1,0)})", "Archetype representation": "frozenset({b-y(1,0), title(0), s-x(1,0)})", "Archetype": 1, "Master": "0", "Best mapping": {"1": -1, "0": 0}, "Best role mapping": {"0": "Title", "1": "Content"}, "Comparisons": 1500}, "11": {"Responsitivity": 1.0, "Time": 1.828318, "New slide": "frozenset({title(0), d-y(0,1), s-x(1,0)})", "Archetype representation": "frozenset({b-y(1,0), title(0), s-x(1,0)})", "Archetype": 1, "Master": "0", "Best mapping": {"1": -1, "0": 0}, "Best role mapping": {"0": "Title", "1": "Content"}, "Comparisons": 10500}, "12": {"Responsitivity": 1.0, "Time": 86.970852, "New slide": "frozenset({b-y(1,0), b-x(0,2), s-x(0,1), b-y(0,2), title(0), d-y(1,2), d-x(1,2), background(2)})", "Archetype representation": "frozenset({b-y(1,0), s-x(0,1), b-x(0,2), b-x(1,2), title(0), d-y(1,2), b-y(2,0)})", "Archetype": 2, "Master": "0", "Best mapping": {"2": -2, "1": -1, "0": 0}, "Best role mapping": {"0": "Title", "1": "Left Content", "2": "Right Content"}, "Comparisons": 160500}}